[
  {
    "bookName": "Isaiah",
    "chapter": 12,
    "verse": 1,
    "text": "At that time you will say: \u201CI praise you, O Lord, for even though you were angry with me, your anger subsided, and you consoled me.",
    "reference": "Isaiah 12:1"
  },
  {
    "bookName": "Isaiah",
    "chapter": 12,
    "verse": 2,
    "text": "Look, God is my deliverer! I will trust in him and not fear. For the Lord gives me strength and protects me; he has become my deliverer.\u201D ",
    "reference": "Isaiah 12:2"
  },
  {
    "bookName": "Isaiah",
    "chapter": 12,
    "verse": 3,
    "text": "Joyfully you will draw water from the springs of deliverance. ",
    "reference": "Isaiah 12:3"
  },
  {
    "bookName": "Isaiah",
    "chapter": 12,
    "verse": 4,
    "text": "At that time you will say: \u201CPraise the Lord! Ask him for help! Publicize his mighty acts among the nations. Make it known that he is unique. ",
    "reference": "Isaiah 12:4"
  },
  {
    "bookName": "Isaiah",
    "chapter": 12,
    "verse": 5,
    "text": "Sing to the Lord, for he has done magnificent things; let this be known throughout the earth. ",
    "reference": "Isaiah 12:5"
  },
  {
    "bookName": "Isaiah",
    "chapter": 12,
    "verse": 6,
    "text": "Cry out and shout for joy, O citizens of Zion, for the Holy One of Israel acts mightily among you!\u201D",
    "reference": "Isaiah 12:6"
  }
]